pymemfile/__init__.py
pymemfile/file.py
pymemfile-0.0.2.dist-info/LICENSE.md
pymemfile-0.0.2.dist-info/METADATA
pymemfile-0.0.2.dist-info/WHEEL
pymemfile-0.0.2.dist-info/top_level.txt
pymemfile-0.0.2.dist-info/RECORD
