Metadata-Version: 2.1
Name: pymemfile
Version: 0.0.2
Summary: pymemfile - flatten python dict or json
Home-page: https://github.com/kr-g/pymemfile
Author: k.r. goger
Author-email: k.r.goger+pymemfile@gmail.com
License: UNKNOWN
Keywords: python in memory file
Platform: UNKNOWN
Classifier: Development Status :: 3 - Alpha
Classifier: Operating System :: POSIX :: Linux
Classifier: Intended Audience :: Developers
Classifier: Programming Language :: Python :: 3
Classifier: License :: OSI Approved :: GNU Affero General Public License v3 or later (AGPLv3+)
Requires-Python: >=3.6
